{
    "GraphImages": [
        {
            "__typename": "GraphVideo",
            "comments_disabled": false,
            "dimensions": {
                "height": 352,
                "width": 640
            },
            "display_url": "https://scontent-lga3-1.cdninstagram.com/v/t51.2885-15/e35/66326557_696263994168146_505672676859955304_n.jpg?_nc_ht=scontent-lga3-1.cdninstagram.com&_nc_cat=102&_nc_ohc=OR-uSdfqeNAAX_jCfd-&oh=fed53c1587f5ee34b971466b5f2905cb&oe=5E40E491",
            "edge_media_preview_like": {
                "count": 2
            },
            "edge_media_to_caption": {
                "edges": []
            },
            "edge_media_to_comment": {
                "count": 0
            },
            "gating_info": null,
            "id": "2090704136517919465",
            "is_video": true,
            "media_preview": "ACoX5qtKxgjlQlxkg47+lZlbOm/6tv8Ae/pUT0RS3LAsoT/CPzP+NJ9jh/u/qf8AGtFPL2DOM554556dP0qFsbjt6dqzd0k7spau1jlaSlNJW5mFaunyKiEMcfN7+lFFTJXQ0aAuEHQ/z/woNxGe/wCh/wAKKKz5S7nNmkoorYzP/9k=",
            "owner": {
                "id": "8999877838"
            },
            "shortcode": "B0DrFXLlyLp",
            "taken_at_timestamp": 1563452604,
            "thumbnail_resources": [
                {
                    "config_height": 150,
                    "config_width": 150,
                    "src": "https://scontent-lga3-1.cdninstagram.com/v/t51.2885-15/e35/c144.0.352.352a/s150x150/66326557_696263994168146_505672676859955304_n.jpg?_nc_ht=scontent-lga3-1.cdninstagram.com&_nc_cat=102&_nc_ohc=OR-uSdfqeNAAX_jCfd-&oh=2ebe73a403ad05d6429783186b05b88a&oe=5E41E663"
                },
                {
                    "config_height": 240,
                    "config_width": 240,
                    "src": "https://scontent-lga3-1.cdninstagram.com/v/t51.2885-15/e35/c144.0.352.352a/s240x240/66326557_696263994168146_505672676859955304_n.jpg?_nc_ht=scontent-lga3-1.cdninstagram.com&_nc_cat=102&_nc_ohc=OR-uSdfqeNAAX_jCfd-&oh=e1ca96b3ff82df23321d6a68edf41c00&oe=5E41E0D6"
                },
                {
                    "config_height": 320,
                    "config_width": 320,
                    "src": "https://scontent-lga3-1.cdninstagram.com/v/t51.2885-15/e35/c144.0.352.352a/s320x320/66326557_696263994168146_505672676859955304_n.jpg?_nc_ht=scontent-lga3-1.cdninstagram.com&_nc_cat=102&_nc_ohc=OR-uSdfqeNAAX_jCfd-&oh=968a710aa8a1acb7eeccd375200dda68&oe=5E41E92E"
                },
                {
                    "config_height": 480,
                    "config_width": 480,
                    "src": "https://scontent-lga3-1.cdninstagram.com/v/t51.2885-15/e35/c144.0.352.352a/66326557_696263994168146_505672676859955304_n.jpg?_nc_ht=scontent-lga3-1.cdninstagram.com&_nc_cat=102&_nc_ohc=OR-uSdfqeNAAX_jCfd-&oh=e45a7d1f46c78a482415ee1e1bab9d33&oe=5E40F9A3"
                },
                {
                    "config_height": 640,
                    "config_width": 640,
                    "src": "https://scontent-lga3-1.cdninstagram.com/v/t51.2885-15/e35/c144.0.352.352a/66326557_696263994168146_505672676859955304_n.jpg?_nc_ht=scontent-lga3-1.cdninstagram.com&_nc_cat=102&_nc_ohc=OR-uSdfqeNAAX_jCfd-&oh=e45a7d1f46c78a482415ee1e1bab9d33&oe=5E40F9A3"
                }
            ],
            "thumbnail_src": "https://scontent-lga3-1.cdninstagram.com/v/t51.2885-15/e35/c144.0.352.352a/66326557_696263994168146_505672676859955304_n.jpg?_nc_ht=scontent-lga3-1.cdninstagram.com&_nc_cat=102&_nc_ohc=OR-uSdfqeNAAX_jCfd-&oh=e45a7d1f46c78a482415ee1e1bab9d33&oe=5E40F9A3",
            "urls": [
                "https://scontent-lga3-1.cdninstagram.com/v/t50.2886-16/67278310_1524444987692413_1781719962021845452_n.mp4?_nc_ht=scontent-lga3-1.cdninstagram.com&_nc_cat=101&_nc_ohc=FtZpNyI6PQUAX_aJubi&oe=5E41D945&oh=4d6274f101c9b449556a37682d75682c"
            ],
            "username": "timur_bekmond",
            "video_view_count": 2861
        }
    ]
}